crickly/__init__.py
crickly/playcricket/__init__.py
crickly/playcricket/admin.py
crickly/playcricket/apps.py
crickly/playcricket/models.py
crickly/playcricket/tests.py
crickly/playcricket/views.py
crickly/playcricket/management/__init__.py
crickly/playcricket/management/commands/__init__.py
crickly/playcricket/management/commands/createmvpscores.py
crickly/playcricket/management/commands/createplayervalues.py
crickly/playcricket/management/commands/fetchmatchdetails.py
crickly/playcricket/management/commands/fetchparscores.py
crickly/playcricket/management/commands/fetchresultdetails.py
crickly/playcricket/migrations/0001_initial.py
crickly/playcricket/migrations/0002_auto_20190110_1822.py
crickly/playcricket/migrations/0003_auto_20190127_1747.py
crickly/playcricket/migrations/0004_auto_20190127_1757.py
crickly/playcricket/migrations/__init__.py
crickly_playcricket-0.1.0.dist-info/LICENSE
crickly_playcricket-0.1.0.dist-info/METADATA
crickly_playcricket-0.1.0.dist-info/WHEEL
crickly_playcricket-0.1.0.dist-info/top_level.txt
crickly_playcricket-0.1.0.dist-info/RECORD
