Metadata-Version: 2.1
Name: crickly-playcricket
Version: 0.1.0
Summary: An extension for crickly to link with the ECB Play Cricket system
Home-page: https://rly.rocks/s/crickly
Author: Riley Evans
Author-email: crickly@rileyevans.co.uk
License: MIT License
Platform: UNKNOWN
Classifier: Environment :: Web Environment
Classifier: Framework :: Django
Classifier: Intended Audience :: Developers
Classifier: Operating System :: OS Independent
Classifier: Programming Language :: Python
Classifier: Programming Language :: Python :: 3.5
Classifier: Programming Language :: Python :: 3.6
Classifier: Topic :: Internet :: WWW/HTTP
Classifier: Topic :: Internet :: WWW/HTTP :: Dynamic Content
Requires-Dist: crickly
